Metadata-Version: 2.1
Name: tools-doc-sphinx
Version: 0.1.1
Summary: Tools for automatic generation of files used in Sphinx documentation
Home-page: https://github.com/RphWbr/tools_doc_sphinx
Author: Raphael Weber
Author-email: raphael.weber@univ-rennes1.fr
License: CeCILL
Platform: UNKNOWN
Classifier: Development Status :: 4 - Beta
Classifier: Operating System :: OS Independent
Classifier: Intended Audience :: Science/Research
Classifier: Intended Audience :: Developers
Classifier: Programming Language :: Python :: 3
Classifier: Programming Language :: Python :: 3.7
Classifier: Programming Language :: Python :: 3.8
Classifier: Programming Language :: Python :: 3.9
Classifier: License :: OSI Approved :: CEA CNRS Inria Logiciel Libre License, version 2.1 (CeCILL-2.1)
Requires-Python: >=3.6, <4
License-File: LICENSE.txt
